django_returnfields/__init__.py
django_returnfields/aggressive.py
django_returnfields/app.py
django_returnfields/constants.py
django_returnfields/optimize.py
django_returnfields/structures.py
django_returnfields-0.3.2.dist-info/DESCRIPTION.rst
django_returnfields-0.3.2.dist-info/entry_points.txt
django_returnfields-0.3.2.dist-info/METADATA
django_returnfields-0.3.2.dist-info/metadata.json
django_returnfields-0.3.2.dist-info/RECORD
django_returnfields-0.3.2.dist-info/top_level.txt
django_returnfields-0.3.2.dist-info/WHEEL
