Metadata-Version: 2.0
Name: django-returnfields
Version: 0.3.2
Summary: adding restriction of your api's return fields, in restframework
Home-page: https://github.com/podhmo/django-returnfields
Author: podhmo
Author-email: UNKNOWN
License: UNKNOWN
Keywords: django restframework return_fields
Platform: UNKNOWN
Classifier: Programming Language :: Python
Classifier: Programming Language :: Python :: Implementation :: CPython
Classifier: Programming Language :: Python :: 3 :: Only
Classifier: Framework :: Django
Classifier: License :: OSI Approved :: BSD License
Requires-Dist: django (>=1.9)
Requires-Dist: djangorestframework
Requires-Dist: django-aggressivequery
Provides-Extra: docs
Provides-Extra: testing
Requires-Dist: tox; extra == 'testing'
